{
  "display_name": "Humble Farmer Merchant",
  "villager_biome": "minecraft:savanna",
  "villager_profession": "minecraft:farmer",
  "trades": [
    {
      "input": {
        "id": "cobblemon:relic_coin",
        "count": 16
      },
      "output": {
        "id": "luckyswardrobe:farmer_hat",
        "count": 1
      }
    },
    {
      "input": {
        "id": "cobblemon:relic_coin",
        "count": 1
      },
      "output": {
        "id": "minecraft:wheat_seeds",
        "count": 1
      }
    },
    {
      "input": {
        "id": "cobblemon:relic_coin",
        "count": 3
      },
      "output": {
        "id": "vegandelight:soybean",
        "count": 1
      }
    },
    {
      "input": {
        "id": "cobblemon:relic_coin",
        "count": 1
      },
      "output": {
        "id": "minecraft:rotten_flesh",
        "count": 16
      }
    },
    {
      "input": {
        "id": "cobblemon:relic_coin",
        "count": 1
      },
      "output": {
        "id": "minecraft:bone",
        "count": 8
      }
    },
    {
      "input": {
        "id": "cobblemon:relic_coin",
        "count": 8
      },
      "output": {
        "id": "extradelight:apple_sapling",
        "count": 1
      }
    }
  ]
}
